{
  "zonesCrossNominees": [
    [
      {
        "inZone": [
          false,
          true
        ],
        "crossingPair": [
          {
            "time": "2015-01-08T02:18:47Z",
            "lat": -33.36135,
            "fix": 184,
            "lng": 147.927683,
            "alt": 625
          },
          {
            "time": "2015-01-08T02:18:48Z",
            "lat": -33.36145,
            "fix": 185,
            "lng": 147.927883,
            "alt": 628
          }
        ]
      },
      {
        "inZone": [
          true,
          false
        ],
        "crossingPair": [
          {
            "time": "2015-01-08T02:20:27Z",
            "lat": -33.3642,
            "fix": 284,
            "lng": 147.930933,
            "alt": 884
          },
          {
            "time": "2015-01-08T02:20:28Z",
            "lat": -33.364417,
            "fix": 285,
            "lng": 147.93095,
            "alt": 888
          }
        ]
      }
    ],
    [
      {
        "inZone": [
          true,
          false
        ],
        "crossingPair": [
          {
            "time": "2015-01-08T03:01:25Z",
            "lat": -33.441567,
            "fix": 2742,
            "lng": 147.980567,
            "alt": 2141
          },
          {
            "time": "2015-01-08T03:01:26Z",
            "lat": -33.4417,
            "fix": 2743,
            "lng": 147.9807,
            "alt": 2141
          }
        ]
      }
    ],
    [
      {
        "inZone": [
          false,
          true
        ],
        "crossingPair": [
          {
            "time": "2015-01-08T04:20:50Z",
            "lat": -33.81915,
            "fix": 7507,
            "lng": 148.087583,
            "alt": 2272
          },
          {
            "time": "2015-01-08T04:20:51Z",
            "lat": -33.8193,
            "fix": 7508,
            "lng": 148.087617,
            "alt": 2270
          }
        ]
      },
      {
        "inZone": [
          true,
          false
        ],
        "crossingPair": [
          {
            "time": "2015-01-08T04:22:00Z",
            "lat": -33.822383,
            "fix": 7577,
            "lng": 148.081283,
            "alt": 2162
          },
          {
            "time": "2015-01-08T04:22:01Z",
            "lat": -33.82235,
            "fix": 7578,
            "lng": 148.081167,
            "alt": 2160
          }
        ]
      }
    ],
    [
      {
        "inZone": [
          false,
          true
        ],
        "crossingPair": [
          {
            "time": "2015-01-08T05:07:22Z",
            "lat": -33.796783,
            "fix": 10299,
            "lng": 147.895583,
            "alt": 553
          },
          {
            "time": "2015-01-08T05:07:23Z",
            "lat": -33.7968,
            "fix": 10300,
            "lng": 147.89545,
            "alt": 553
          }
        ]
      }
    ],
    []
  ],
  "zonesCrossExcluded": [],
  "startSelected": [
    "2015-01-08T03:00:00Z",
    {
      "inZone": [
        true,
        false
      ],
      "crossingPair": [
        {
          "time": "2015-01-08T03:01:25Z",
          "lat": -33.441567,
          "fix": 2742,
          "lng": 147.980567,
          "alt": 2141
        },
        {
          "time": "2015-01-08T03:01:26Z",
          "lat": -33.4417,
          "fix": 2743,
          "lng": 147.9807,
          "alt": 2141
        }
      ]
    }
  ],
  "zonesCrossSelected": [
    {
      "inZone": [
        false,
        true
      ],
      "crossingPair": [
        {
          "time": "2015-01-08T02:18:47Z",
          "lat": -33.36135,
          "fix": 184,
          "lng": 147.927683,
          "alt": 625
        },
        {
          "time": "2015-01-08T02:18:48Z",
          "lat": -33.36145,
          "fix": 185,
          "lng": 147.927883,
          "alt": 628
        }
      ]
    },
    {
      "inZone": [
        true,
        false
      ],
      "crossingPair": [
        {
          "time": "2015-01-08T03:01:25Z",
          "lat": -33.441567,
          "fix": 2742,
          "lng": 147.980567,
          "alt": 2141
        },
        {
          "time": "2015-01-08T03:01:26Z",
          "lat": -33.4417,
          "fix": 2743,
          "lng": 147.9807,
          "alt": 2141
        }
      ]
    },
    {
      "inZone": [
        false,
        true
      ],
      "crossingPair": [
        {
          "time": "2015-01-08T04:20:50Z",
          "lat": -33.81915,
          "fix": 7507,
          "lng": 148.087583,
          "alt": 2272
        },
        {
          "time": "2015-01-08T04:20:51Z",
          "lat": -33.8193,
          "fix": 7508,
          "lng": 148.087617,
          "alt": 2270
        }
      ]
    },
    {
      "inZone": [
        false,
        true
      ],
      "crossingPair": [
        {
          "time": "2015-01-08T05:07:22Z",
          "lat": -33.796783,
          "fix": 10299,
          "lng": 147.895583,
          "alt": 553
        },
        {
          "time": "2015-01-08T05:07:23Z",
          "lat": -33.7968,
          "fix": 10300,
          "lng": 147.89545,
          "alt": 553
        }
      ]
    },
    null
  ],
  "startNominees": [
    [
      "2015-01-08T03:30:00Z",
      []
    ],
    [
      "2015-01-08T03:15:00Z",
      []
    ],
    [
      "2015-01-08T03:00:00Z",
      [
        {
          "inZone": [
            true,
            false
          ],
          "crossingPair": [
            {
              "time": "2015-01-08T03:01:25Z",
              "lat": -33.441567,
              "fix": 2742,
              "lng": 147.980567,
              "alt": 2141
            },
            {
              "time": "2015-01-08T03:01:26Z",
              "lat": -33.4417,
              "fix": 2743,
              "lng": 147.9807,
              "alt": 2141
            }
          ]
        }
      ]
    ],
    [
      "2015-01-08T02:45:00Z",
      []
    ]
  ]
}
