{
  "zonesCrossNominees": [
    [],
    [
      {
        "inZone": [
          true,
          false
        ],
        "crossingPair": [
          {
            "time": "2015-01-02T02:44:41Z",
            "lat": -33.414,
            "fix": 570,
            "lng": 147.84481667,
            "alt": 1234
          },
          {
            "time": "2015-01-02T02:44:46Z",
            "lat": -33.41475,
            "fix": 571,
            "lng": 147.84441667,
            "alt": 1239
          }
        ]
      },
      {
        "inZone": [
          false,
          true
        ],
        "crossingPair": [
          {
            "time": "2015-01-02T02:45:31Z",
            "lat": -33.41668333,
            "fix": 580,
            "lng": 147.84601667,
            "alt": 1238
          },
          {
            "time": "2015-01-02T02:45:36Z",
            "lat": -33.4164,
            "fix": 581,
            "lng": 147.84698333,
            "alt": 1212
          }
        ]
      },
      {
        "inZone": [
          true,
          false
        ],
        "crossingPair": [
          {
            "time": "2015-01-02T02:45:55Z",
            "lat": -33.41666667,
            "fix": 586,
            "lng": 147.8477,
            "alt": 1140
          },
          {
            "time": "2015-01-02T02:46:00Z",
            "lat": -33.4173,
            "fix": 587,
            "lng": 147.84706667,
            "alt": 1134
          }
        ]
      }
    ],
    [
      {
        "inZone": [
          false,
          true
        ],
        "crossingPair": [
          {
            "time": "2015-01-02T04:11:54Z",
            "lat": -33.74981667,
            "fix": 1615,
            "lng": 147.52743333,
            "alt": 1753
          },
          {
            "time": "2015-01-02T04:11:56Z",
            "lat": -33.75005,
            "fix": 1616,
            "lng": 147.52773333,
            "alt": 1757
          }
        ]
      },
      {
        "inZone": [
          true,
          false
        ],
        "crossingPair": [
          {
            "time": "2015-01-02T04:12:02Z",
            "lat": -33.74991667,
            "fix": 1618,
            "lng": 147.52826667,
            "alt": 1759
          },
          {
            "time": "2015-01-02T04:12:07Z",
            "lat": -33.74968333,
            "fix": 1619,
            "lng": 147.52775,
            "alt": 1769
          }
        ]
      },
      {
        "inZone": [
          false,
          true
        ],
        "crossingPair": [
          {
            "time": "2015-01-02T04:12:12Z",
            "lat": -33.74986667,
            "fix": 1620,
            "lng": 147.52705,
            "alt": 1767
          },
          {
            "time": "2015-01-02T04:12:17Z",
            "lat": -33.75056667,
            "fix": 1621,
            "lng": 147.52646667,
            "alt": 1769
          }
        ]
      },
      {
        "inZone": [
          true,
          false
        ],
        "crossingPair": [
          {
            "time": "2015-01-02T04:13:57Z",
            "lat": -33.75671667,
            "fix": 1641,
            "lng": 147.53015,
            "alt": 1739
          },
          {
            "time": "2015-01-02T04:14:03Z",
            "lat": -33.75763333,
            "fix": 1642,
            "lng": 147.53056667,
            "alt": 1728
          }
        ]
      }
    ],
    [
      {
        "inZone": [
          false,
          true
        ],
        "crossingPair": [
          {
            "time": "2015-01-02T05:59:52Z",
            "lat": -34.08168333,
            "fix": 2909,
            "lng": 148.01773333,
            "alt": 2347
          },
          {
            "time": "2015-01-02T05:59:57Z",
            "lat": -34.08175,
            "fix": 2910,
            "lng": 148.01901667,
            "alt": 2334
          }
        ]
      },
      {
        "inZone": [
          true,
          false
        ],
        "crossingPair": [
          {
            "time": "2015-01-02T06:00:34Z",
            "lat": -34.08475,
            "fix": 2918,
            "lng": 148.02033333,
            "alt": 2295
          },
          {
            "time": "2015-01-02T06:00:39Z",
            "lat": -34.08505,
            "fix": 2919,
            "lng": 148.01923333,
            "alt": 2283
          }
        ]
      }
    ],
    [
      {
        "inZone": [
          false,
          true
        ],
        "crossingPair": [
          {
            "time": "2015-01-02T07:14:38Z",
            "lat": -34.49543333,
            "fix": 3803,
            "lng": 147.89783333,
            "alt": 725
          },
          {
            "time": "2015-01-02T07:14:43Z",
            "lat": -34.4967,
            "fix": 3804,
            "lng": 147.8976,
            "alt": 710
          }
        ]
      },
      {
        "inZone": [
          true,
          false
        ],
        "crossingPair": [
          {
            "time": "2015-01-02T07:15:21Z",
            "lat": -34.50346667,
            "fix": 3833,
            "lng": 147.89695,
            "alt": 614
          },
          {
            "time": "2015-01-02T07:15:22Z",
            "lat": -34.50355,
            "fix": 3834,
            "lng": 147.89708333,
            "alt": 613
          }
        ]
      },
      {
        "inZone": [
          false,
          true
        ],
        "crossingPair": [
          {
            "time": "2015-01-02T07:17:23Z",
            "lat": -34.50176667,
            "fix": 3954,
            "lng": 147.90036667,
            "alt": 363
          },
          {
            "time": "2015-01-02T07:17:25Z",
            "lat": -34.50178333,
            "fix": 3955,
            "lng": 147.90023333,
            "alt": 357
          }
        ]
      }
    ]
  ],
  "zonesCrossExcluded": [],
  "startSelected": [
    "2015-01-02T02:45:00Z",
    {
      "inZone": [
        true,
        false
      ],
      "crossingPair": [
        {
          "time": "2015-01-02T02:45:55Z",
          "lat": -33.41666667,
          "fix": 586,
          "lng": 147.8477,
          "alt": 1140
        },
        {
          "time": "2015-01-02T02:46:00Z",
          "lat": -33.4173,
          "fix": 587,
          "lng": 147.84706667,
          "alt": 1134
        }
      ]
    }
  ],
  "zonesCrossSelected": [
    null,
    {
      "inZone": [
        true,
        false
      ],
      "crossingPair": [
        {
          "time": "2015-01-02T02:45:55Z",
          "lat": -33.41666667,
          "fix": 586,
          "lng": 147.8477,
          "alt": 1140
        },
        {
          "time": "2015-01-02T02:46:00Z",
          "lat": -33.4173,
          "fix": 587,
          "lng": 147.84706667,
          "alt": 1134
        }
      ]
    },
    {
      "inZone": [
        false,
        true
      ],
      "crossingPair": [
        {
          "time": "2015-01-02T04:11:54Z",
          "lat": -33.74981667,
          "fix": 1615,
          "lng": 147.52743333,
          "alt": 1753
        },
        {
          "time": "2015-01-02T04:11:56Z",
          "lat": -33.75005,
          "fix": 1616,
          "lng": 147.52773333,
          "alt": 1757
        }
      ]
    },
    {
      "inZone": [
        false,
        true
      ],
      "crossingPair": [
        {
          "time": "2015-01-02T05:59:52Z",
          "lat": -34.08168333,
          "fix": 2909,
          "lng": 148.01773333,
          "alt": 2347
        },
        {
          "time": "2015-01-02T05:59:57Z",
          "lat": -34.08175,
          "fix": 2910,
          "lng": 148.01901667,
          "alt": 2334
        }
      ]
    },
    {
      "inZone": [
        false,
        true
      ],
      "crossingPair": [
        {
          "time": "2015-01-02T07:14:38Z",
          "lat": -34.49543333,
          "fix": 3803,
          "lng": 147.89783333,
          "alt": 725
        },
        {
          "time": "2015-01-02T07:14:43Z",
          "lat": -34.4967,
          "fix": 3804,
          "lng": 147.8976,
          "alt": 710
        }
      ]
    }
  ],
  "startNominees": [
    [
      "2015-01-02T03:45:00Z",
      []
    ],
    [
      "2015-01-02T03:30:00Z",
      []
    ],
    [
      "2015-01-02T03:15:00Z",
      []
    ],
    [
      "2015-01-02T03:00:00Z",
      []
    ],
    [
      "2015-01-02T02:45:00Z",
      [
        {
          "inZone": [
            true,
            false
          ],
          "crossingPair": [
            {
              "time": "2015-01-02T02:45:55Z",
              "lat": -33.41666667,
              "fix": 586,
              "lng": 147.8477,
              "alt": 1140
            },
            {
              "time": "2015-01-02T02:46:00Z",
              "lat": -33.4173,
              "fix": 587,
              "lng": 147.84706667,
              "alt": 1134
            }
          ]
        }
      ]
    ]
  ]
}
