[
  {
    "inter": {
      "time": "2015-01-08T01:33:13.11198214557Z",
      "lat": -33.3571872,
      "fixFrac": 72.31119821455799,
      "lng": 147.93216003,
      "alt": 889.42
    },
    "cross": {
      "inZone": [
        false,
        true
      ],
      "crossingPair": [
        {
          "time": "2015-01-08T01:33:10Z",
          "lat": -33.35661667,
          "fix": 72,
          "lng": 147.93206667,
          "alt": 886
        },
        {
          "time": "2015-01-08T01:33:20Z",
          "lat": -33.35845,
          "fix": 73,
          "lng": 147.93236667,
          "alt": 897
        }
      ]
    }
  },
  {
    "inter": {
      "time": "2015-01-08T02:45:46.46567197813Z",
      "lat": -33.39554638,
      "fixFrac": 508.4465671978131,
      "lng": 148.03191645,
      "alt": 1828.64
    },
    "cross": {
      "inZone": [
        true,
        false
      ],
      "crossingPair": [
        {
          "time": "2015-01-08T02:45:42Z",
          "lat": -33.39475,
          "fix": 508,
          "lng": 148.03156667,
          "alt": 1834
        },
        {
          "time": "2015-01-08T02:45:52Z",
          "lat": -33.39653333,
          "fix": 509,
          "lng": 148.03235,
          "alt": 1822
        }
      ]
    }
  },
  {
    "inter": {
      "time": "2015-01-08T03:50:20.994748534645Z",
      "lat": -33.83204268,
      "fixFrac": 895.7989497069292,
      "lng": 148.06897577,
      "alt": 2420.19
    },
    "cross": {
      "inZone": [
        false,
        true
      ],
      "crossingPair": [
        {
          "time": "2015-01-08T03:50:17Z",
          "lat": -33.83155,
          "fix": 895,
          "lng": 148.06828333,
          "alt": 2413
        },
        {
          "time": "2015-01-08T03:50:22Z",
          "lat": -33.83216667,
          "fix": 896,
          "lng": 148.06915,
          "alt": 2422
        }
      ]
    }
  },
  {
    "inter": {
      "time": "2015-01-08T04:11:26.046800515264Z",
      "lat": -33.81096606,
      "fixFrac": 1023.1495429307529,
      "lng": 147.89972629,
      "alt": 1296.76
    },
    "cross": {
      "inZone": [
        false,
        true
      ],
      "crossingPair": [
        {
          "time": "2015-01-08T04:11:25Z",
          "lat": -33.81103333,
          "fix": 1023,
          "lng": 147.89988333,
          "alt": 1299
        },
        {
          "time": "2015-01-08T04:11:32Z",
          "lat": -33.81058333,
          "fix": 1024,
          "lng": 147.89883333,
          "alt": 1284
        }
      ]
    }
  },
  {
    "inter": {
      "time": "2015-01-08T05:12:15.330409897947Z",
      "lat": -33.61855595,
      "fixFrac": 1404.3304098979477,
      "lng": 148.40901072,
      "alt": 511.34
    },
    "cross": {
      "inZone": [
        false,
        true
      ],
      "crossingPair": [
        {
          "time": "2015-01-08T05:12:15Z",
          "lat": -33.6186,
          "fix": 1404,
          "lng": 148.40896667,
          "alt": 512
        },
        {
          "time": "2015-01-08T05:12:16Z",
          "lat": -33.61846667,
          "fix": 1405,
          "lng": 148.4091,
          "alt": 510
        }
      ]
    }
  }
]
