[
  {
    "inter": {
      "time": "2015-01-08T01:32:55.60897345468Z",
      "lat": -33.35718483,
      "fixFrac": 57.9608973454684,
      "lng": 147.93203241,
      "alt": 1024.12
    },
    "cross": {
      "inZone": [
        false,
        true
      ],
      "crossingPair": [
        {
          "time": "2015-01-08T01:32:46Z",
          "lat": -33.35558333,
          "fix": 57,
          "lng": 147.9316,
          "alt": 1027
        },
        {
          "time": "2015-01-08T01:32:56Z",
          "lat": -33.35725,
          "fix": 58,
          "lng": 147.93205,
          "alt": 1024
        }
      ]
    }
  },
  {
    "inter": {
      "time": "2015-01-08T02:46:45.81539728446Z",
      "lat": -33.44281923,
      "fixFrac": 502.3815397284462,
      "lng": 147.97748227,
      "alt": 1525.66
    },
    "cross": {
      "inZone": [
        true,
        false
      ],
      "crossingPair": [
        {
          "time": "2015-01-08T02:46:42Z",
          "lat": -33.44218333,
          "fix": 502,
          "lng": 147.97766667,
          "alt": 1531
        },
        {
          "time": "2015-01-08T02:46:52Z",
          "lat": -33.44385,
          "fix": 503,
          "lng": 147.97718333,
          "alt": 1517
        }
      ]
    }
  },
  {
    "inter": {
      "time": "2015-01-08T03:58:27.48120878771Z",
      "lat": -33.83780438,
      "fixFrac": 932.4962417575423,
      "lng": 148.06443359,
      "alt": 1265.98
    },
    "cross": {
      "inZone": [
        false,
        true
      ],
      "crossingPair": [
        {
          "time": "2015-01-08T03:58:25Z",
          "lat": -33.83728333,
          "fix": 932,
          "lng": 148.06446667,
          "alt": 1263
        },
        {
          "time": "2015-01-08T03:58:30Z",
          "lat": -33.83833333,
          "fix": 933,
          "lng": 148.0644,
          "alt": 1269
        }
      ]
    }
  },
  {
    "inter": {
      "time": "2015-01-08T04:28:35.54958561245Z",
      "lat": -33.81773978,
      "fixFrac": 1114.0785122303505,
      "lng": 147.90106009,
      "alt": 1768.67
    },
    "cross": {
      "inZone": [
        false,
        true
      ],
      "crossingPair": [
        {
          "time": "2015-01-08T04:28:35Z",
          "lat": -33.8178,
          "fix": 1114,
          "lng": 147.90113333,
          "alt": 1770
        },
        {
          "time": "2015-01-08T04:28:42Z",
          "lat": -33.81703333,
          "fix": 1115,
          "lng": 147.9002,
          "alt": 1753
        }
      ]
    }
  },
  null
]
