[
  null,
  {
    "inter": {
      "time": "2015-01-01T03:00:57.906602137467Z",
      "lat": -33.34185157,
      "fixFrac": 1981.3022007124896,
      "lng": 147.98111502,
      "alt": 0
    },
    "cross": {
      "inZone": [
        true,
        false
      ],
      "crossingPair": [
        {
          "time": "2015-01-01T03:00:57Z",
          "lat": -33.34186667,
          "fix": 1981,
          "lng": 147.98088333,
          "alt": 0
        },
        {
          "time": "2015-01-01T03:01:00Z",
          "lat": -33.34181667,
          "fix": 1982,
          "lng": 147.98165,
          "alt": 0
        }
      ]
    }
  },
  {
    "inter": {
      "time": "2015-01-01T04:18:34.486760355428Z",
      "lat": -33.55260044,
      "fixFrac": 3527.828920118477,
      "lng": 148.66736928,
      "alt": 0
    },
    "cross": {
      "inZone": [
        false,
        true
      ],
      "crossingPair": [
        {
          "time": "2015-01-01T04:18:32Z",
          "lat": -33.55268333,
          "fix": 3527,
          "lng": 148.66681667,
          "alt": 0
        },
        {
          "time": "2015-01-01T04:18:35Z",
          "lat": -33.55258333,
          "fix": 3528,
          "lng": 148.66748333,
          "alt": 0
        }
      ]
    }
  },
  {
    "inter": {
      "time": "2015-01-01T05:23:22.67635534045Z",
      "lat": -33.12891993,
      "fixFrac": 4819.225451780151,
      "lng": 148.83178739,
      "alt": 0
    },
    "cross": {
      "inZone": [
        false,
        true
      ],
      "crossingPair": [
        {
          "time": "2015-01-01T05:23:22Z",
          "lat": -33.12895,
          "fix": 4819,
          "lng": 148.83163333,
          "alt": 0
        },
        {
          "time": "2015-01-01T05:23:25Z",
          "lat": -33.12881667,
          "fix": 4820,
          "lng": 148.83231667,
          "alt": 0
        }
      ]
    }
  },
  {
    "inter": {
      "time": "2015-01-01T05:36:59.123631093459Z",
      "lat": -33.18488596,
      "fixFrac": 5090.707877031154,
      "lng": 148.6814704,
      "alt": 0
    },
    "cross": {
      "inZone": [
        false,
        true
      ],
      "crossingPair": [
        {
          "time": "2015-01-01T05:36:57Z",
          "lat": -33.18465,
          "fix": 5090,
          "lng": 148.68188333,
          "alt": 0
        },
        {
          "time": "2015-01-01T05:37:00Z",
          "lat": -33.18498333,
          "fix": 5091,
          "lng": 148.6813,
          "alt": 0
        }
      ]
    }
  }
]
