[
  {
    "inter": {
      "time": "2015-01-03T02:01:00.793133276428Z",
      "lat": -33.35724311,
      "fixFrac": 308.9310444254765,
      "lng": 147.93122529,
      "alt": 1346.1
    },
    "cross": {
      "inZone": [
        false,
        true
      ],
      "crossingPair": [
        {
          "time": "2015-01-03T02:00:58Z",
          "lat": -33.3567,
          "fix": 308,
          "lng": 147.93111667,
          "alt": 1334
        },
        {
          "time": "2015-01-03T02:01:01Z",
          "lat": -33.35728333,
          "fix": 309,
          "lng": 147.93123333,
          "alt": 1347
        }
      ]
    }
  },
  {
    "inter": {
      "time": "2015-01-03T02:45:29.098390053976Z",
      "lat": -33.42283308,
      "fixFrac": 1198.3661300179924,
      "lng": 147.85327141,
      "alt": 2102.9
    },
    "cross": {
      "inZone": [
        true,
        false
      ],
      "crossingPair": [
        {
          "time": "2015-01-03T02:45:28Z",
          "lat": -33.42265,
          "fix": 1198,
          "lng": 147.85346667,
          "alt": 2104
        },
        {
          "time": "2015-01-03T02:45:31Z",
          "lat": -33.42315,
          "fix": 1199,
          "lng": 147.85293333,
          "alt": 2101
        }
      ]
    }
  },
  {
    "inter": {
      "time": "2015-01-03T03:59:34.805510054172Z",
      "lat": -34.14962746,
      "fixFrac": 2662.6018366847247,
      "lng": 147.39970217,
      "alt": 1769.59
    },
    "cross": {
      "inZone": [
        false,
        true
      ],
      "crossingPair": [
        {
          "time": "2015-01-03T03:59:33Z",
          "lat": -34.14936667,
          "fix": 2662,
          "lng": 147.40008333,
          "alt": 1772
        },
        {
          "time": "2015-01-03T03:59:36Z",
          "lat": -34.1498,
          "fix": 2663,
          "lng": 147.39945,
          "alt": 1768
        }
      ]
    }
  },
  {
    "inter": {
      "time": "2015-01-03T04:53:54.410039110011Z",
      "lat": -34.40896618,
      "fixFrac": 3749.136679703338,
      "lng": 146.85522494,
      "alt": 2151.86
    },
    "cross": {
      "inZone": [
        false,
        true
      ],
      "crossingPair": [
        {
          "time": "2015-01-03T04:53:54Z",
          "lat": -34.40885,
          "fix": 3749,
          "lng": 146.85525,
          "alt": 2152
        },
        {
          "time": "2015-01-03T04:53:57Z",
          "lat": -34.4097,
          "fix": 3750,
          "lng": 146.85506667,
          "alt": 2151
        }
      ]
    }
  },
  {
    "inter": {
      "time": "2015-01-03T05:13:41.103224143785Z",
      "lat": -34.71594075,
      "fixFrac": 4144.701074714595,
      "lng": 146.77558777,
      "alt": 452
    },
    "cross": {
      "inZone": [
        false,
        true
      ],
      "crossingPair": [
        {
          "time": "2015-01-03T05:13:39Z",
          "lat": -34.71545,
          "fix": 4144,
          "lng": 146.77595,
          "alt": 452
        },
        {
          "time": "2015-01-03T05:13:42Z",
          "lat": -34.71615,
          "fix": 4145,
          "lng": 146.77543333,
          "alt": 452
        }
      ]
    }
  }
]
