[
  {
    "inter": {
      "time": "2015-01-06T02:40:18.16191753043Z",
      "lat": -33.36376984,
      "fixFrac": 93.31619175304346,
      "lng": 147.92953162,
      "alt": 1096.11
    },
    "cross": {
      "inZone": [
        false,
        true
      ],
      "crossingPair": [
        {
          "time": "2015-01-06T02:40:15Z",
          "lat": -33.36403333,
          "fix": 93,
          "lng": 147.9295,
          "alt": 1092
        },
        {
          "time": "2015-01-06T02:40:25Z",
          "lat": -33.3632,
          "fix": 94,
          "lng": 147.9296,
          "alt": 1105
        }
      ]
    }
  },
  {
    "inter": {
      "time": "2015-01-06T03:00:04.0953816318Z",
      "lat": -33.3762238,
      "fixFrac": 212.80953816318055,
      "lng": 147.88113808,
      "alt": 1654.95
    },
    "cross": {
      "inZone": [
        true,
        false
      ],
      "crossingPair": [
        {
          "time": "2015-01-06T02:59:56Z",
          "lat": -33.37646667,
          "fix": 212,
          "lng": 147.88215,
          "alt": 1659
        },
        {
          "time": "2015-01-06T03:00:06Z",
          "lat": -33.37616667,
          "fix": 213,
          "lng": 147.8809,
          "alt": 1654
        }
      ]
    }
  },
  {
    "inter": {
      "time": "2015-01-06T05:41:42.29018558156Z",
      "lat": -33.41640736,
      "fixFrac": 1180.7150309302608,
      "lng": 146.75824171,
      "alt": 1651.41
    },
    "cross": {
      "inZone": [
        false,
        true
      ],
      "crossingPair": [
        {
          "time": "2015-01-06T05:41:38Z",
          "lat": -33.41621667,
          "fix": 1180,
          "lng": 146.75935,
          "alt": 1665
        },
        {
          "time": "2015-01-06T05:41:44Z",
          "lat": -33.41648333,
          "fix": 1181,
          "lng": 146.7578,
          "alt": 1646
        }
      ]
    }
  },
  {
    "inter": {
      "time": "2015-01-06T07:24:03.02557921571Z",
      "lat": -33.79713166,
      "fixFrac": 1793.8025579215716,
      "lng": 146.26339584,
      "alt": 2544.58
    },
    "cross": {
      "inZone": [
        false,
        true
      ],
      "crossingPair": [
        {
          "time": "2015-01-06T07:23:55Z",
          "lat": -33.79556667,
          "fix": 1793,
          "lng": 146.26365,
          "alt": 2551
        },
        {
          "time": "2015-01-06T07:24:05Z",
          "lat": -33.79751667,
          "fix": 1794,
          "lng": 146.26333333,
          "alt": 2543
        }
      ]
    }
  },
  null
]
